cli/__init__.py
cli/cli.py
cli/utils/__init__.py
cli/utils/get_files.py
parser/__init__.py
parser/engine.py
parser/main.py
envyro-0.5.0.dist-info/METADATA
envyro-0.5.0.dist-info/WHEEL
envyro-0.5.0.dist-info/entry_points.txt
envyro-0.5.0.dist-info/RECORD
