Metadata-Version: 2.4
Name: envyro
Version: 0.5.0
Summary: Environment manager with multi-env parsing
Requires-Python: >=3.10
Requires-Dist: pyyaml>=6.0
Requires-Dist: rich>=14.0.0
Requires-Dist: tomli-w>=1.0.0
Requires-Dist: typer>=0.16.0
